metevolsim/__init__.py
metevolsim/metevolsim.py
MetEvolSim-1.0.0.dist-info/LICENSE.txt
MetEvolSim-1.0.0.dist-info/METADATA
MetEvolSim-1.0.0.dist-info/WHEEL
MetEvolSim-1.0.0.dist-info/top_level.txt
MetEvolSim-1.0.0.dist-info/RECORD
