Metadata-Version: 2.1
Name: MetEvolSim
Version: 1.0.0
Summary: MetEvolSim (Metabolome Evolution Simulator) Python Package
Home-page: https://github.com/charlesrocabert/MetEvolSim
Author: Charles Rocabert, Gábor Boross, Orsolya Liska, Balázs Papp
Author-email: 
License: GNU General Public License v3 (GPLv3)
Project-URL: Source, https://github.com/charlesrocabert/MetEvolSim
Keywords: simulation evolution systems-biology sbml copasi metabolism metabolome abundances metabolic-network kinetic-model evolution-rate
Classifier: Development Status :: 4 - Beta
Classifier: Programming Language :: Python :: 3
Classifier: License :: OSI Approved :: GNU General Public License v3 (GPLv3)
Classifier: Operating System :: OS Independent
Classifier: Intended Audience :: Science/Research
Classifier: Topic :: Scientific/Engineering :: Bio-Informatics
Requires-Python: >=3
License-File: LICENSE.txt
Requires-Dist: python-libsbml
Requires-Dist: numpy
Requires-Dist: networkx
